MANIFEST.in
setup.py
Boutique.egg-info/PKG-INFO
Boutique.egg-info/SOURCES.txt
Boutique.egg-info/dependency_links.txt
Boutique.egg-info/entry_points.txt
Boutique.egg-info/not-zip-safe
Boutique.egg-info/requires.txt
Boutique.egg-info/top_level.txt
boutiqueclient/__init__.py
boutiqueclient/app.py
boutiqueclient/boutique.py
boutiqueclient/bservice/__init__.py
boutiqueclient/bservice/api/__init__.py
boutiqueclient/bservice/api/credentials.py
boutiqueclient/bservice/api/error.py
boutiqueclient/bservice/api/response.py
boutiqueclient/bservice/api/service.py
boutiqueclient/bservice/cmds/__init__.py
boutiqueclient/bservice/cmds/auth.py
boutiqueclient/bservice/cmds/base.py
boutiqueclient/bservice/cmds/server.py
boutiqueclient/bservice/cmds/site.py
boutiqueclient/bsite/__init__.py
boutiqueclient/bsite/template.py
boutiqueclient/bsite/views.py
boutiqueclient/bsite/objects/__init__.py
boutiqueclient/bsite/objects/cart.py
boutiqueclient/bsite/objects/db.py
boutiqueclient/bsite/objects/linklist.py
boutiqueclient/bsite/objects/product.py
boutiqueclient/bsite/objects/site.py
boutiqueclient/bsite/objects/base/__init__.py
boutiqueclient/bsite/objects/base/fields.py
boutiqueclient/bsite/objects/base/obj.py