Metadata-Version: 1.0
Name: Boutique
Version: 0.1.3
Summary: 
